{
	"info": {
		"_postman_id": "5c7e6716-aa3f-47c3-901c-d88ff619cff5",
		"name": "fm-inventory",
		"schema": "https://schema.getpostman.com/json/collection/v2.1.0/collection.json",
		"_exporter_id": "19791325",
		"_collection_link": "https://nepal-commerce.postman.co/workspace/Team-Workspace~630496f0-e11e-435b-88ad-db2d0a326979/collection/19791325-5c7e6716-aa3f-47c3-901c-d88ff619cff5?action=share&creator=19791325&source=collection_link"
	},
	"item": [
		{
			"name": "Category",
			"item": [
				{
					"name": "store",
					"request": {
						"method": "POST",
						"header": [
							{
								"key": "organizationId",
								"value": "33d5fc59-963d-4bb6-b429-117ee601826d",
								"type": "text"
							}
						],
						"body": {
							"mode": "formdata",
							"formdata": [
								{
									"key": "title",
									"value": "Sub Title 2",
									"type": "text"
								},
								{
									"key": "detail",
									"value": "alkdsjwjaldjald\nadklwjalkjsdkljwakl",
									"type": "text"
								},
								{
									"key": "inventory_forecast_id",
									"value": "asd",
									"type": "text"
								},
								{
									"key": "parent_id",
									"value": "4",
									"type": "text"
								},
								{
									"key": "status",
									"value": "0",
									"type": "text",
									"disabled": true
								}
							]
						},
						"url": {
							"raw": "{{url}}/api/category",
							"host": [
								"{{url}}"
							],
							"path": [
								"api",
								"category"
							]
						}
					},
					"response": []
				},
				{
					"name": "update",
					"request": {
						"method": "POST",
						"header": [
							{
								"key": "organizationId",
								"value": "33d5fc59-963d-4bb6-b429-117ee601826d",
								"type": "text"
							}
						],
						"body": {
							"mode": "formdata",
							"formdata": [
								{
									"key": "title",
									"value": "Title 1 Edited",
									"type": "text"
								},
								{
									"key": "detail",
									"value": "alkdsjwjaldjald\nadklwjalkjsdkljwakl",
									"type": "text",
									"disabled": true
								},
								{
									"key": "inventory_forecast_id",
									"value": "asdws",
									"type": "text"
								},
								{
									"key": "parent_id",
									"value": "2",
									"type": "text"
								},
								{
									"key": "_method",
									"value": "PUT",
									"type": "text"
								}
							]
						},
						"url": {
							"raw": "{{url}}/api/category/:category_id",
							"host": [
								"{{url}}"
							],
							"path": [
								"api",
								"category",
								":category_id"
							],
							"variable": [
								{
									"key": "category_id",
									"value": "3"
								}
							]
						}
					},
					"response": []
				},
				{
					"name": "index",
					"request": {
						"auth": {
							"type": "bearer",
							"bearer": [
								{
									"key": "token",
									"value": "{{access_token}}",
									"type": "string"
								}
							]
						},
						"method": "GET",
						"header": [
							{
								"key": "organizationId",
								"value": "{{organization_id}}",
								"type": "text"
							},
							{
								"key": "Accept",
								"value": "application/json",
								"type": "text"
							}
						],
						"url": {
							"raw": "{{url}}/api/category?status=&sort_key=TITLE&sort_order=asc&paginate=1&limit=2",
							"host": [
								"{{url}}"
							],
							"path": [
								"api",
								"category"
							],
							"query": [
								{
									"key": "status",
									"value": ""
								},
								{
									"key": "sort_key",
									"value": "TITLE"
								},
								{
									"key": "sort_order",
									"value": "asc"
								},
								{
									"key": "paginate",
									"value": "1"
								},
								{
									"key": "limit",
									"value": "2"
								}
							]
						}
					},
					"response": []
				},
				{
					"name": "find by id",
					"request": {
						"method": "GET",
						"header": [
							{
								"key": "organizationId",
								"value": "33d5fc59-963d-4bb6-b429-117ee601826d",
								"type": "text"
							}
						],
						"url": {
							"raw": "{{url}}/api/category/:category_id",
							"host": [
								"{{url}}"
							],
							"path": [
								"api",
								"category",
								":category_id"
							],
							"variable": [
								{
									"key": "category_id",
									"value": "2"
								}
							]
						}
					},
					"response": []
				},
				{
					"name": "delete",
					"request": {
						"method": "DELETE",
						"header": [
							{
								"key": "organizationId",
								"value": "{{organization_id}}",
								"type": "text"
							}
						],
						"url": {
							"raw": "{{url}}/api/category/:category_id",
							"host": [
								"{{url}}"
							],
							"path": [
								"api",
								"category",
								":category_id"
							],
							"variable": [
								{
									"key": "category_id",
									"value": "1"
								}
							]
						}
					},
					"response": []
				}
			]
		},
		{
			"name": "Discount",
			"item": [
				{
					"name": "store",
					"request": {
						"method": "POST",
						"header": [
							{
								"key": "organizationId",
								"value": "{{organization_id}}",
								"type": "text"
							},
							{
								"key": "Accept",
								"value": "application/json",
								"type": "text"
							}
						],
						"body": {
							"mode": "raw",
							"raw": "{\r\n    \"campaign_title\": \"Title\",\r\n    \"percentage\": 50.11,\r\n    \"start_date\": \"2022-02-02\",\r\n    \"end_date\": \"2023-01-01\",\r\n    \"created_by\": \"awldkj2lj3109-1231\",\r\n    \"approved_by\": \"alkdjw2-192310-13\",\r\n    \"status\": \"inprogress\",\r\n    \"item_ids\": [1, 2, 4]\r\n}",
							"options": {
								"raw": {
									"language": "json"
								}
							}
						},
						"url": {
							"raw": "{{url}}/api/discount",
							"host": [
								"{{url}}"
							],
							"path": [
								"api",
								"discount"
							]
						}
					},
					"response": []
				},
				{
					"name": "update",
					"request": {
						"method": "POST",
						"header": [
							{
								"key": "organizationId",
								"value": "33d5fc59-963d-4bb6-b429-117ee601826d",
								"type": "text"
							}
						],
						"body": {
							"mode": "raw",
							"raw": "{\r\n    \"campaign_title\": \"Title edited\",\r\n    \"percentage\": 55.11,\r\n    \"start_date\": \"2022-01-01\",\r\n    \"end_date\": \"2023-01-01\",\r\n    \"created_by\": \"awldkj2lj3109-1231\",\r\n    \"approved_by\": \"alkdjw2-192310-14\",\r\n    \"status\": \"inprogress\",\r\n    \"item_ids\": [5,7,8],\r\n    \"_method\": \"PUT\"\r\n}",
							"options": {
								"raw": {
									"language": "json"
								}
							}
						},
						"url": {
							"raw": "{{url}}/api/discount/:discount_id",
							"host": [
								"{{url}}"
							],
							"path": [
								"api",
								"discount",
								":discount_id"
							],
							"variable": [
								{
									"key": "discount_id",
									"value": "3"
								}
							]
						}
					},
					"response": []
				},
				{
					"name": "index",
					"request": {
						"auth": {
							"type": "bearer",
							"bearer": [
								{
									"key": "token",
									"value": "{{access_token}}",
									"type": "string"
								}
							]
						},
						"method": "GET",
						"header": [
							{
								"key": "organizationId",
								"value": "33d5fc59-963d-4bb6-b429-117ee601826d",
								"type": "text"
							},
							{
								"key": "Accept",
								"value": "application/json",
								"type": "text"
							}
						],
						"url": {
							"raw": "{{url}}/api/discount?status=",
							"host": [
								"{{url}}"
							],
							"path": [
								"api",
								"discount"
							],
							"query": [
								{
									"key": "status",
									"value": "",
									"description": "values: [approved, inprogress, pending]"
								}
							]
						}
					},
					"response": []
				},
				{
					"name": "find by id",
					"request": {
						"method": "GET",
						"header": [
							{
								"key": "organizationId",
								"value": "33d5fc59-963d-4bb6-b429-117ee601826d",
								"type": "text"
							},
							{
								"key": "Accept",
								"value": "application/json",
								"type": "text"
							}
						],
						"url": {
							"raw": "{{url}}/api/discount/:discount_id",
							"host": [
								"{{url}}"
							],
							"path": [
								"api",
								"discount",
								":discount_id"
							],
							"variable": [
								{
									"key": "discount_id",
									"value": "3"
								}
							]
						}
					},
					"response": []
				},
				{
					"name": "delete",
					"request": {
						"method": "DELETE",
						"header": [
							{
								"key": "organizationId",
								"value": "33d5fc59-963d-4bb6-b429-117ee601826d",
								"type": "text"
							}
						],
						"url": {
							"raw": "{{url}}/api/discount/:discount_id",
							"host": [
								"{{url}}"
							],
							"path": [
								"api",
								"discount",
								":discount_id"
							],
							"variable": [
								{
									"key": "discount_id",
									"value": "3"
								}
							]
						}
					},
					"response": []
				}
			]
		},
		{
			"name": "Vendor",
			"item": [
				{
					"name": "store",
					"request": {
						"method": "POST",
						"header": [
							{
								"key": "organizationId",
								"value": "33d5fc59-963d-4bb6-b429-117ee601826d",
								"type": "text"
							}
						],
						"body": {
							"mode": "formdata",
							"formdata": [
								{
									"key": "name",
									"value": "Bishal Gurung",
									"type": "text"
								},
								{
									"key": "phone",
									"value": "1231",
									"type": "text"
								},
								{
									"key": "email",
									"value": "asdw@gmai.com",
									"type": "text"
								},
								{
									"key": "contact_persion",
									"value": "1312",
									"type": "text"
								},
								{
									"key": "status",
									"value": "0",
									"type": "text"
								}
							]
						},
						"url": {
							"raw": "{{url}}/api/vendor",
							"host": [
								"{{url}}"
							],
							"path": [
								"api",
								"vendor"
							]
						}
					},
					"response": []
				},
				{
					"name": "update",
					"request": {
						"method": "POST",
						"header": [
							{
								"key": "Accept",
								"value": "application/json",
								"type": "text"
							},
							{
								"key": "organizationId",
								"value": "33d5fc59-963d-4bb6-b429-117ee601826d",
								"type": "text"
							}
						],
						"body": {
							"mode": "formdata",
							"formdata": [
								{
									"key": "name",
									"value": "Bishal Gurung",
									"type": "text"
								},
								{
									"key": "phone",
									"value": "989898",
									"type": "text",
									"disabled": true
								},
								{
									"key": "email",
									"value": "grgbishal360@gmail.com",
									"type": "text",
									"disabled": true
								},
								{
									"key": "contact_persion",
									"value": "awalkjddkl",
									"type": "text",
									"disabled": true
								},
								{
									"key": "status",
									"value": "1",
									"type": "text"
								},
								{
									"key": "_method",
									"value": "PUT",
									"type": "text"
								}
							]
						},
						"url": {
							"raw": "{{url}}/api/vendor/:vendor_id",
							"host": [
								"{{url}}"
							],
							"path": [
								"api",
								"vendor",
								":vendor_id"
							],
							"variable": [
								{
									"key": "vendor_id",
									"value": "1"
								}
							]
						}
					},
					"response": []
				},
				{
					"name": "index",
					"request": {
						"method": "GET",
						"header": [
							{
								"key": "organizationId",
								"value": "33d5fc59-963d-4bb6-b429-117ee601826d",
								"type": "text"
							}
						],
						"url": {
							"raw": "{{url}}/api/vendor?status=&paginate=&limit=&sort_key=&sort_order=",
							"host": [
								"{{url}}"
							],
							"path": [
								"api",
								"vendor"
							],
							"query": [
								{
									"key": "status",
									"value": ""
								},
								{
									"key": "paginate",
									"value": ""
								},
								{
									"key": "limit",
									"value": ""
								},
								{
									"key": "sort_key",
									"value": ""
								},
								{
									"key": "sort_order",
									"value": ""
								}
							]
						}
					},
					"response": []
				},
				{
					"name": "find by id",
					"request": {
						"method": "GET",
						"header": [
							{
								"key": "organizationId",
								"value": "{{organization_id}}",
								"type": "text"
							}
						],
						"url": {
							"raw": "{{url}}/api/vendor/:vendor_id",
							"host": [
								"{{url}}"
							],
							"path": [
								"api",
								"vendor",
								":vendor_id"
							],
							"variable": [
								{
									"key": "vendor_id",
									"value": "1"
								}
							]
						}
					},
					"response": []
				},
				{
					"name": "delete",
					"request": {
						"method": "DELETE",
						"header": [
							{
								"key": "organizationId",
								"value": "{{organization_id}}",
								"type": "text"
							}
						],
						"url": {
							"raw": "{{url}}/api/vendor/:vendor_id",
							"host": [
								"{{url}}"
							],
							"path": [
								"api",
								"vendor",
								":vendor_id"
							],
							"variable": [
								{
									"key": "vendor_id",
									"value": "1"
								}
							]
						}
					},
					"response": []
				}
			]
		},
		{
			"name": "Coshh",
			"item": [
				{
					"name": "store",
					"request": {
						"method": "POST",
						"header": [
							{
								"key": "organizationId",
								"value": "33d5fc59-963d-4bb6-b429-117ee601826d",
								"type": "text"
							},
							{
								"key": "Accept",
								"value": "application/json",
								"type": "text"
							}
						],
						"body": {
							"mode": "formdata",
							"formdata": [
								{
									"key": "name",
									"value": "Coshh 2",
									"type": "text"
								},
								{
									"key": "description",
									"value": "alsdjlakjd\nasjdlkwjdaklsjdklsajdwa\n",
									"type": "text"
								},
								{
									"key": "safety_guidelines",
									"value": "aldjwaidj\nadlkwajdwlkjdalkd",
									"type": "text"
								},
								{
									"key": "image",
									"type": "file",
									"src": "/C:/Users/Leon Schiffer/Downloads/download (2).png"
								},
								{
									"key": "status",
									"value": "",
									"type": "text",
									"disabled": true
								}
							]
						},
						"url": {
							"raw": "{{url}}/api/coshh",
							"host": [
								"{{url}}"
							],
							"path": [
								"api",
								"coshh"
							]
						}
					},
					"response": []
				},
				{
					"name": "update",
					"request": {
						"method": "POST",
						"header": [
							{
								"key": "Accept",
								"value": "application/json",
								"type": "text"
							},
							{
								"key": "organizationId",
								"value": "33d5fc59-963d-4bb6-b429-117ee601826d",
								"type": "text"
							}
						],
						"body": {
							"mode": "formdata",
							"formdata": [
								{
									"key": "name",
									"value": "Coshh 1 edited",
									"type": "text"
								},
								{
									"key": "description",
									"value": "alsdjlakjd\nasjdlkwjdaklsjdklsajdwa\n",
									"type": "text"
								},
								{
									"key": "safety_guidelines",
									"value": "ald",
									"type": "text"
								},
								{
									"key": "status",
									"value": "0",
									"type": "text"
								},
								{
									"key": "image",
									"type": "file",
									"src": "/C:/Users/Leon Schiffer/Downloads/memes/261734489_10159672452874886_5687370738635405381_n.jpg"
								},
								{
									"key": "_method",
									"value": "PUT",
									"type": "text"
								}
							]
						},
						"url": {
							"raw": "{{url}}/api/coshh/:coshh_id",
							"host": [
								"{{url}}"
							],
							"path": [
								"api",
								"coshh",
								":coshh_id"
							],
							"variable": [
								{
									"key": "coshh_id",
									"value": "3"
								}
							]
						}
					},
					"response": []
				},
				{
					"name": "index",
					"request": {
						"method": "GET",
						"header": [
							{
								"key": "organizationId",
								"value": "{{organization_id}}",
								"type": "text"
							}
						],
						"url": {
							"raw": "{{url}}/api/coshh?status=&paginate=&limit=&sort_key=name&sort_order=asc",
							"host": [
								"{{url}}"
							],
							"path": [
								"api",
								"coshh"
							],
							"query": [
								{
									"key": "status",
									"value": ""
								},
								{
									"key": "paginate",
									"value": ""
								},
								{
									"key": "limit",
									"value": ""
								},
								{
									"key": "sort_key",
									"value": "name"
								},
								{
									"key": "sort_order",
									"value": "asc"
								}
							]
						}
					},
					"response": []
				},
				{
					"name": "find by id",
					"request": {
						"method": "GET",
						"header": [
							{
								"key": "organizationId",
								"value": "33d5fc59-963d-4bb6-b429-117ee601826d",
								"type": "text"
							}
						],
						"url": {
							"raw": "{{url}}/api/coshh/:coshh_id",
							"host": [
								"{{url}}"
							],
							"path": [
								"api",
								"coshh",
								":coshh_id"
							],
							"variable": [
								{
									"key": "coshh_id",
									"value": "2"
								}
							]
						}
					},
					"response": []
				}
			]
		},
		{
			"name": "Client Group",
			"item": [
				{
					"name": "store",
					"request": {
						"method": "POST",
						"header": [
							{
								"key": "organizationId",
								"value": "33d5fc59-963d-4bb6-b429-117ee601826d",
								"type": "text"
							},
							{
								"key": "Accept",
								"value": "application/json",
								"type": "text"
							}
						],
						"body": {
							"mode": "raw",
							"raw": "{\r\n    \"name\": \"Client Group 3\",\r\n    \"client_ids\": [\r\n        1,\r\n        2,\r\n        \"asd-123\"\r\n    ],\r\n    \"status\": 1\r\n}",
							"options": {
								"raw": {
									"language": "json"
								}
							}
						},
						"url": {
							"raw": "{{url}}/api/client-group",
							"host": [
								"{{url}}"
							],
							"path": [
								"api",
								"client-group"
							]
						}
					},
					"response": []
				},
				{
					"name": "update",
					"request": {
						"method": "POST",
						"header": [
							{
								"key": "Accept",
								"value": "application/json",
								"type": "text"
							},
							{
								"key": "organizationId",
								"value": "33d5fc59-963d-4bb6-b429-117ee601826d",
								"type": "text"
							}
						],
						"body": {
							"mode": "raw",
							"raw": "{\r\n    \"name\" : \"Client Group Edited\",\r\n    \"client_ids\" : [1,4,5],\r\n    \"status\" : 1,\r\n    \"_method\" : \"PUT\"\r\n}",
							"options": {
								"raw": {
									"language": "json"
								}
							}
						},
						"url": {
							"raw": "{{url}}/api/client-group/:client_group_id",
							"host": [
								"{{url}}"
							],
							"path": [
								"api",
								"client-group",
								":client_group_id"
							],
							"variable": [
								{
									"key": "client_group_id",
									"value": "9"
								}
							]
						}
					},
					"response": []
				},
				{
					"name": "index",
					"request": {
						"method": "GET",
						"header": [
							{
								"key": "organizationId",
								"value": "{{organization_id}}",
								"type": "text"
							}
						],
						"url": {
							"raw": "{{url}}/api/client-group?status=1&paginate=&limit=&sort_key=name&sort_order=asc",
							"host": [
								"{{url}}"
							],
							"path": [
								"api",
								"client-group"
							],
							"query": [
								{
									"key": "status",
									"value": "1"
								},
								{
									"key": "paginate",
									"value": ""
								},
								{
									"key": "limit",
									"value": ""
								},
								{
									"key": "sort_key",
									"value": "name"
								},
								{
									"key": "sort_order",
									"value": "asc"
								}
							]
						}
					},
					"response": []
				},
				{
					"name": "find by id",
					"request": {
						"method": "GET",
						"header": [
							{
								"key": "organizationId",
								"value": "33d5fc59-963d-4bb6-b429-117ee601826d",
								"type": "text"
							},
							{
								"key": "Accept",
								"value": "application/json",
								"type": "text"
							}
						],
						"url": {
							"raw": "{{url}}/api/client-group/:client_group_id",
							"host": [
								"{{url}}"
							],
							"path": [
								"api",
								"client-group",
								":client_group_id"
							],
							"variable": [
								{
									"key": "client_group_id",
									"value": "6"
								}
							]
						}
					},
					"response": []
				},
				{
					"name": "find client group by client id",
					"request": {
						"auth": {
							"type": "bearer",
							"bearer": [
								{
									"key": "token",
									"value": "{{access_token}}",
									"type": "string"
								}
							]
						},
						"method": "GET",
						"header": [
							{
								"key": "organizationId",
								"value": "{{organization_id}}",
								"type": "text"
							},
							{
								"key": "Accept",
								"value": "application/json",
								"type": "text"
							}
						],
						"url": {
							"raw": "{{url}}/api/client-group/:client_id/client",
							"host": [
								"{{url}}"
							],
							"path": [
								"api",
								"client-group",
								":client_id",
								"client"
							],
							"variable": [
								{
									"key": "client_id",
									"value": "1"
								}
							]
						}
					},
					"response": []
				},
				{
					"name": "get occupied client ids",
					"request": {
						"method": "GET",
						"header": [
							{
								"key": "organizationId",
								"value": "33d5fc59-963d-4bb6-b429-117ee601826d",
								"type": "text"
							},
							{
								"key": "Accept",
								"value": "application/json",
								"type": "text"
							}
						],
						"url": {
							"raw": "{{url}}/api/client-group/client-ids-occupied",
							"host": [
								"{{url}}"
							],
							"path": [
								"api",
								"client-group",
								"client-ids-occupied"
							]
						}
					},
					"response": []
				}
			]
		},
		{
			"name": "Item",
			"item": [
				{
					"name": "Item Variation",
					"item": [
						{
							"name": "update item variation stock quantity",
							"request": {
								"method": "POST",
								"header": [
									{
										"key": "Accept",
										"value": "application/json",
										"type": "text"
									},
									{
										"key": "organizationId",
										"value": "{{organization_id}}",
										"type": "text"
									}
								],
								"body": {
									"mode": "raw",
									"raw": "{\r\n    \"quantity\": \"3\",\r\n    \"_method\": \"PATCH\"\r\n}",
									"options": {
										"raw": {
											"language": "json"
										}
									}
								},
								"url": {
									"raw": "{{url}}/api/item-variation/:item_variation_id/quantity",
									"host": [
										"{{url}}"
									],
									"path": [
										"api",
										"item-variation",
										":item_variation_id",
										"quantity"
									],
									"variable": [
										{
											"key": "item_variation_id",
											"value": "1"
										}
									]
								}
							},
							"response": []
						}
					]
				},
				{
					"name": "store",
					"request": {
						"auth": {
							"type": "bearer",
							"bearer": [
								{
									"key": "token",
									"value": "{{access_token}}",
									"type": "string"
								}
							]
						},
						"method": "POST",
						"header": [
							{
								"key": "organizationId",
								"value": "{{organization_id}}",
								"type": "text"
							},
							{
								"key": "Accept",
								"value": "application/json",
								"type": "text"
							}
						],
						"body": {
							"mode": "raw",
							"raw": "{\r\n    \"name\": \"Item 1\",\r\n    \"price\": 123,\r\n    \"description\": \"alsdjlakjd↵asjdlkwjdaklsjdklsajdwa\",\r\n    \"used_for\": \"adws\",\r\n    \"category_id\": 1,\r\n    \"coshh_ids\": [1,3],\r\n    \"status\":1,\r\n    \"variations\": [\r\n        {\r\n            \"vendor_id\": \"123ads\",\r\n            \"size\": \"large\",\r\n            \"color\": \"black\",\r\n            \"unit_id\": 1,\r\n            \"margin\": 20.44,\r\n            \"buying_price\": 200,\r\n            \"selling_price\": 250,\r\n            \"discount\": 5.3,\r\n            \"quantity\": 5,\r\n            \"sku\": \"sku123\"\r\n        },\r\n        {\r\n            \"vendor_id\": \"123ads\",\r\n            \"size\": \"medium\",\r\n            \"color\": \"pink\",\r\n            \"unit_id\": 1,\r\n            \"margin\": 23.238,\r\n            \"buying_price\": 300,\r\n            \"selling_price\": 350,\r\n            \"discount\": 15.3,\r\n            \"quantity\": 2,\r\n            \"sku\": \"sku124\"\r\n        },\r\n        {\r\n            \"vendor_id\": \"123ads\",\r\n            \"size\": \"xxl\",\r\n            \"color\": \"white\",\r\n            \"unit_id\": 3,\r\n            \"buying_price\": 400,\r\n            \"selling_price\": 450,\r\n            \"discount\": 25.3,\r\n            \"quantity\": 8,\r\n            \"sku\": \"sku125\"\r\n        }\r\n    ],\r\n    \"risk_assessments\": {\r\n        \"abc\" : \"ab\",\r\n        \"b\": \"bcde\"\r\n    }\r\n}",
							"options": {
								"raw": {
									"language": "json"
								}
							}
						},
						"url": {
							"raw": "{{url}}/api/item",
							"host": [
								"{{url}}"
							],
							"path": [
								"api",
								"item"
							]
						}
					},
					"response": []
				},
				{
					"name": "update",
					"request": {
						"method": "POST",
						"header": [
							{
								"key": "Accept",
								"value": "application/json",
								"type": "text"
							},
							{
								"key": "organizationId",
								"value": "{{organization_id}}",
								"type": "text"
							}
						],
						"body": {
							"mode": "raw",
							"raw": "{\r\n    \"name\": \"Item 1 edited\",\r\n    \"price\": 123,\r\n    \"description\": \"alsdjlakjd↵asjdlkwjdaklsjdklsajdwa\",\r\n    \"used_for\": \"adws\",\r\n    \"category_id\": 4,\r\n    \"sub_category_id\":2,\r\n    \"coshh_ids\": [1,3],\r\n    \"status\":1,\r\n    \"variations\": [\r\n        {\r\n            \"id\": 28,\r\n            \"vendor_id\": \"123\",\r\n            \"size\": \"L\",\r\n            \"color\": \"Black\",\r\n            \"unit_id\": 1,\r\n            \"margin\": 15,\r\n            \"buying_price\": 3200,\r\n            \"selling_price\": 350,\r\n            \"discount\": 35.3,\r\n            \"quantity\": null,\r\n            \"sku\": \"sku123\"\r\n        },\r\n        \r\n        {\r\n            \"id\": 29,\r\n            \"vendor_id\": \"123\",\r\n            \"size\": \"XXL\",\r\n            \"unit_id\": 3,\r\n            \"margin\": 20,\r\n            \"color\": \"White\",\r\n            \"buying_price\": 500,\r\n            \"selling_price\": 550,\r\n            \"discount\": 55.3,\r\n            \"quantity\": 8,\r\n            \"sku\": \"sku125\"\r\n        }\r\n    ],\r\n    \"risk_assessments\": {\r\n        \"abc\" : \"ab\",\r\n        \"b\": \"bcde\"\r\n    },\r\n    \"_method\": \"PUT\"\r\n}",
							"options": {
								"raw": {
									"language": "json"
								}
							}
						},
						"url": {
							"raw": "{{url}}/api/item/:item_id",
							"host": [
								"{{url}}"
							],
							"path": [
								"api",
								"item",
								":item_id"
							],
							"variable": [
								{
									"key": "item_id",
									"value": "9"
								}
							]
						}
					},
					"response": []
				},
				{
					"name": "index",
					"request": {
						"method": "GET",
						"header": [
							{
								"key": "organizationId",
								"value": "{{organization_id}}",
								"type": "text"
							}
						],
						"url": {
							"raw": "{{url}}/api/item?status=&paginate=1&limit=100&sort_key=id&sort_order=asc&coshh_id=&category_id=&sub_category_id=&client_id=",
							"host": [
								"{{url}}"
							],
							"path": [
								"api",
								"item"
							],
							"query": [
								{
									"key": "status",
									"value": ""
								},
								{
									"key": "paginate",
									"value": "1"
								},
								{
									"key": "limit",
									"value": "100"
								},
								{
									"key": "sort_key",
									"value": "id"
								},
								{
									"key": "sort_order",
									"value": "asc"
								},
								{
									"key": "coshh_id",
									"value": ""
								},
								{
									"key": "category_id",
									"value": ""
								},
								{
									"key": "sub_category_id",
									"value": ""
								},
								{
									"key": "client_id",
									"value": ""
								}
							]
						}
					},
					"response": []
				},
				{
					"name": "find by id",
					"request": {
						"method": "GET",
						"header": [
							{
								"key": "organizationId",
								"value": "33d5fc59-963d-4bb6-b429-117ee601826d",
								"type": "text"
							}
						],
						"url": {
							"raw": "{{url}}/api/item/:item_id",
							"host": [
								"{{url}}"
							],
							"path": [
								"api",
								"item",
								":item_id"
							],
							"variable": [
								{
									"key": "item_id",
									"value": "1"
								}
							]
						}
					},
					"response": []
				},
				{
					"name": "delete",
					"request": {
						"method": "DELETE",
						"header": [
							{
								"key": "organizationId",
								"value": "33d5fc59-963d-4bb6-b429-117ee601826d",
								"type": "text"
							}
						],
						"url": {
							"raw": "{{url}}/api/item/:item_id",
							"host": [
								"{{url}}"
							],
							"path": [
								"api",
								"item",
								":item_id"
							],
							"variable": [
								{
									"key": "item_id",
									"value": "2"
								}
							]
						}
					},
					"response": []
				},
				{
					"name": "add items by client group",
					"request": {
						"method": "POST",
						"header": [
							{
								"key": "organizationId",
								"value": "33d5fc59-963d-4bb6-b429-117ee601826d",
								"type": "text"
							},
							{
								"key": "Accept",
								"value": "application/json",
								"type": "text"
							}
						],
						"body": {
							"mode": "raw",
							"raw": "{\r\n    \"item_variation_ids\" : [1,2,3,4]\r\n}",
							"options": {
								"raw": {
									"language": "json"
								}
							}
						},
						"url": {
							"raw": "{{url}}/api/item/:client_group_id/client-group",
							"host": [
								"{{url}}"
							],
							"path": [
								"api",
								"item",
								":client_group_id",
								"client-group"
							],
							"variable": [
								{
									"key": "client_group_id",
									"value": "5"
								}
							]
						}
					},
					"response": []
				},
				{
					"name": "add items by client id",
					"request": {
						"method": "POST",
						"header": [
							{
								"key": "organizationId",
								"value": "33d5fc59-963d-4bb6-b429-117ee601826d",
								"type": "text"
							},
							{
								"key": "Accept",
								"value": "application/json",
								"type": "text"
							}
						],
						"body": {
							"mode": "raw",
							"raw": "{\r\n    \"item_variation_ids\" : [2,3,4]\r\n}",
							"options": {
								"raw": {
									"language": "json"
								}
							}
						},
						"url": {
							"raw": "{{url}}/api/item/:client_id/client-id",
							"host": [
								"{{url}}"
							],
							"path": [
								"api",
								"item",
								":client_id",
								"client-id"
							],
							"variable": [
								{
									"key": "client_id",
									"value": "1"
								}
							]
						}
					},
					"response": []
				}
			]
		},
		{
			"name": "Order",
			"item": [
				{
					"name": "create new order",
					"request": {
						"method": "POST",
						"header": [
							{
								"key": "organizationId",
								"value": "{{organization_id}}",
								"type": "text"
							},
							{
								"key": "Accept",
								"value": "application/json",
								"type": "text"
							}
						],
						"body": {
							"mode": "raw",
							"raw": "{\r\n    \"client_id\": \"1a\",\r\n    \"ordered_by\": \"2b\",\r\n    \"ordered_date\": \"2022/12/13\",\r\n    \"delivery_date\": \"2022/12/25\",\r\n    \"delivery_time\": \"10:20 am\",\r\n    \"status\": \"approved\",\r\n    \"approved_by\": \"\",\r\n    \"details\": [\r\n        {\r\n            \"item_id\": 1,\r\n            \"size\": \"large\",\r\n            \"color\": \"black\",\r\n            \"quantity\": 2\r\n        }\r\n    ]\r\n}",
							"options": {
								"raw": {
									"language": "json"
								}
							}
						},
						"url": {
							"raw": "{{url}}/api/order",
							"host": [
								"{{url}}"
							],
							"path": [
								"api",
								"order"
							]
						}
					},
					"response": []
				},
				{
					"name": "update order",
					"request": {
						"method": "POST",
						"header": [
							{
								"key": "organizationId",
								"value": "{{organization_id}}",
								"type": "text"
							},
							{
								"key": "Accept",
								"value": "application/json",
								"type": "text"
							}
						],
						"body": {
							"mode": "raw",
							"raw": "{\r\n    \"delivery_date\": \"2023/12/25\",\r\n    \"delivery_time\": \"1:36 am\",\r\n    \"approved_by\": \"asdw\",\r\n    \"details\": [\r\n        {\r\n            \"item_id\": 1,\r\n            \"size\": \"large\",\r\n            \"color\": \"black\",\r\n            \"quantity\": 3\r\n        }\r\n        \r\n    ],\r\n    \"_method\": \"PUT\"\r\n}",
							"options": {
								"raw": {
									"language": "json"
								}
							}
						},
						"url": {
							"raw": "{{url}}/api/order/:order_id",
							"host": [
								"{{url}}"
							],
							"path": [
								"api",
								"order",
								":order_id"
							],
							"variable": [
								{
									"key": "order_id",
									"value": "45"
								}
							]
						}
					},
					"response": []
				},
				{
					"name": "update order status",
					"request": {
						"method": "POST",
						"header": [
							{
								"key": "organizationId",
								"value": "{{organization_id}}",
								"type": "text"
							},
							{
								"key": "Accept",
								"value": "application/json",
								"type": "text"
							}
						],
						"body": {
							"mode": "raw",
							"raw": "{\r\n    \"status\": \"pending\",\r\n    \"approved_by\": \"user-126\",\r\n    \"_method\": \"put\"\r\n}",
							"options": {
								"raw": {
									"language": "json"
								}
							}
						},
						"url": {
							"raw": "{{url}}/api/order/:order_id/update-status",
							"host": [
								"{{url}}"
							],
							"path": [
								"api",
								"order",
								":order_id",
								"update-status"
							],
							"variable": [
								{
									"key": "order_id",
									"value": "18"
								}
							]
						}
					},
					"response": []
				},
				{
					"name": "get all orders",
					"request": {
						"method": "GET",
						"header": [
							{
								"key": "organizationId",
								"value": "{{organization_id}}",
								"type": "text"
							},
							{
								"key": "Accept",
								"value": "application/json",
								"type": "text"
							}
						],
						"url": {
							"raw": "{{url}}/api/order?client_id=1a&sort_key=&sort_order=",
							"host": [
								"{{url}}"
							],
							"path": [
								"api",
								"order"
							],
							"query": [
								{
									"key": "client_id",
									"value": "1a"
								},
								{
									"key": "sort_key",
									"value": "",
									"description": "default: \"ordered_date\""
								},
								{
									"key": "sort_order",
									"value": "",
									"description": "values: [\"ASC\", \"DESC\"], default: \"DESC\""
								}
							]
						}
					},
					"response": []
				},
				{
					"name": "get single order",
					"request": {
						"method": "GET",
						"header": [
							{
								"key": "organizationId",
								"value": "{{organization_id}}",
								"type": "text"
							},
							{
								"key": "Accept",
								"value": "application/json",
								"type": "text"
							}
						],
						"url": {
							"raw": "{{url}}/api/order/:order_id",
							"host": [
								"{{url}}"
							],
							"path": [
								"api",
								"order",
								":order_id"
							],
							"variable": [
								{
									"key": "order_id",
									"value": "3"
								}
							]
						}
					},
					"response": []
				},
				{
					"name": "delete order",
					"request": {
						"method": "DELETE",
						"header": [
							{
								"key": "organizationId",
								"value": "{{organization_id}}",
								"type": "text"
							},
							{
								"key": "Accept",
								"value": "application/json",
								"type": "text"
							}
						],
						"url": {
							"raw": "{{url}}/api/order/:order_id",
							"host": [
								"{{url}}"
							],
							"path": [
								"api",
								"order",
								":order_id"
							],
							"variable": [
								{
									"key": "order_id",
									"value": "3"
								}
							]
						}
					},
					"response": []
				}
			]
		},
		{
			"name": "File",
			"item": [
				{
					"name": "upload file",
					"request": {
						"method": "POST",
						"header": [
							{
								"key": "organizationId",
								"value": "{{organization_id}}",
								"type": "text"
							},
							{
								"key": "Accept",
								"value": "application/json",
								"type": "text"
							}
						],
						"body": {
							"mode": "formdata",
							"formdata": [
								{
									"key": "image",
									"type": "file",
									"src": "/C:/Users/Leon Schiffer/Downloads/download (2).png"
								}
							]
						},
						"url": {
							"raw": "{{url}}/api/file",
							"host": [
								"{{url}}"
							],
							"path": [
								"api",
								"file"
							]
						}
					},
					"response": []
				}
			]
		},
		{
			"name": "Color",
			"item": [
				{
					"name": "get all colors",
					"protocolProfileBehavior": {
						"disableBodyPruning": true
					},
					"request": {
						"method": "GET",
						"header": [
							{
								"key": "organizationId",
								"value": "{{organization_id}}",
								"type": "text"
							}
						],
						"body": {
							"mode": "formdata",
							"formdata": []
						},
						"url": {
							"raw": "{{url}}/api/color",
							"host": [
								"{{url}}"
							],
							"path": [
								"api",
								"color"
							]
						}
					},
					"response": []
				},
				{
					"name": "create color",
					"request": {
						"method": "POST",
						"header": [
							{
								"key": "organizationId",
								"value": "{{organization_id}}",
								"type": "text"
							},
							{
								"key": "Accept",
								"value": "application/json",
								"type": "text"
							}
						],
						"body": {
							"mode": "formdata",
							"formdata": [
								{
									"key": "name",
									"value": "Blue",
									"type": "text"
								}
							]
						},
						"url": {
							"raw": "{{url}}/api/color",
							"host": [
								"{{url}}"
							],
							"path": [
								"api",
								"color"
							]
						}
					},
					"response": []
				},
				{
					"name": "update color",
					"request": {
						"method": "POST",
						"header": [
							{
								"key": "organizationId",
								"value": "{{organization_id}}",
								"type": "text"
							}
						],
						"body": {
							"mode": "formdata",
							"formdata": [
								{
									"key": "name",
									"value": "Yellow",
									"type": "text"
								},
								{
									"key": "_method",
									"value": "PUT",
									"type": "text"
								}
							]
						},
						"url": {
							"raw": "{{url}}/api/color/:color_id",
							"host": [
								"{{url}}"
							],
							"path": [
								"api",
								"color",
								":color_id"
							],
							"variable": [
								{
									"key": "color_id",
									"value": "1"
								}
							]
						}
					},
					"response": []
				},
				{
					"name": "delete color",
					"request": {
						"method": "DELETE",
						"header": [
							{
								"key": "organizationId",
								"value": "{{organization_id}}",
								"type": "text"
							}
						],
						"body": {
							"mode": "formdata",
							"formdata": []
						},
						"url": {
							"raw": "{{url}}/api/color/:color_id",
							"host": [
								"{{url}}"
							],
							"path": [
								"api",
								"color",
								":color_id"
							],
							"variable": [
								{
									"key": "color_id",
									"value": "1"
								}
							]
						}
					},
					"response": []
				},
				{
					"name": "get single color",
					"protocolProfileBehavior": {
						"disableBodyPruning": true
					},
					"request": {
						"method": "GET",
						"header": [
							{
								"key": "organizationId",
								"value": "{{organization_id}}",
								"type": "text"
							}
						],
						"body": {
							"mode": "formdata",
							"formdata": []
						},
						"url": {
							"raw": "{{url}}/api/color/:color_id",
							"host": [
								"{{url}}"
							],
							"path": [
								"api",
								"color",
								":color_id"
							],
							"variable": [
								{
									"key": "color_id",
									"value": "2"
								}
							]
						}
					},
					"response": []
				}
			]
		},
		{
			"name": "Unit",
			"item": [
				{
					"name": "get all units",
					"protocolProfileBehavior": {
						"disableBodyPruning": true
					},
					"request": {
						"method": "GET",
						"header": [
							{
								"key": "organizationId",
								"value": "{{organization_id}}",
								"type": "text"
							}
						],
						"body": {
							"mode": "formdata",
							"formdata": []
						},
						"url": {
							"raw": "{{url}}/api/unit",
							"host": [
								"{{url}}"
							],
							"path": [
								"api",
								"unit"
							]
						}
					},
					"response": []
				},
				{
					"name": "create unit",
					"request": {
						"method": "POST",
						"header": [
							{
								"key": "organizationId",
								"value": "{{organization_id}}",
								"type": "text"
							},
							{
								"key": "Accept",
								"value": "application/json",
								"type": "text"
							}
						],
						"body": {
							"mode": "formdata",
							"formdata": [
								{
									"key": "name",
									"value": "Gram",
									"type": "text"
								}
							]
						},
						"url": {
							"raw": "{{url}}/api/unit",
							"host": [
								"{{url}}"
							],
							"path": [
								"api",
								"unit"
							]
						}
					},
					"response": []
				},
				{
					"name": "update color",
					"request": {
						"method": "POST",
						"header": [
							{
								"key": "organizationId",
								"value": "{{organization_id}}",
								"type": "text"
							}
						],
						"body": {
							"mode": "formdata",
							"formdata": [
								{
									"key": "name",
									"value": "Kilo",
									"type": "text"
								},
								{
									"key": "_method",
									"value": "PUT",
									"type": "text"
								}
							]
						},
						"url": {
							"raw": "{{url}}/api/unit/:unit_id",
							"host": [
								"{{url}}"
							],
							"path": [
								"api",
								"unit",
								":unit_id"
							],
							"variable": [
								{
									"key": "unit_id",
									"value": "3"
								}
							]
						}
					},
					"response": []
				},
				{
					"name": "delete color",
					"request": {
						"method": "DELETE",
						"header": [
							{
								"key": "organizationId",
								"value": "{{organization_id}}",
								"type": "text"
							}
						],
						"body": {
							"mode": "formdata",
							"formdata": []
						},
						"url": {
							"raw": "{{url}}/api/unit/:unit_id",
							"host": [
								"{{url}}"
							],
							"path": [
								"api",
								"unit",
								":unit_id"
							],
							"variable": [
								{
									"key": "unit_id",
									"value": "2"
								}
							]
						}
					},
					"response": []
				},
				{
					"name": "get single unit",
					"protocolProfileBehavior": {
						"disableBodyPruning": true
					},
					"request": {
						"method": "GET",
						"header": [
							{
								"key": "organizationId",
								"value": "{{organization_id}}",
								"type": "text"
							}
						],
						"body": {
							"mode": "formdata",
							"formdata": []
						},
						"url": {
							"raw": "{{url}}/api/unit/:unit_id",
							"host": [
								"{{url}}"
							],
							"path": [
								"api",
								"unit",
								":unit_id"
							],
							"variable": [
								{
									"key": "unit_id",
									"value": "3"
								}
							]
						}
					},
					"response": []
				}
			]
		},
		{
			"name": "Size",
			"item": [
				{
					"name": "get all sizes",
					"protocolProfileBehavior": {
						"disableBodyPruning": true
					},
					"request": {
						"method": "GET",
						"header": [
							{
								"key": "organizationId",
								"value": "{{organization_id}}",
								"type": "text"
							}
						],
						"body": {
							"mode": "formdata",
							"formdata": []
						},
						"url": {
							"raw": "{{url}}/api/size",
							"host": [
								"{{url}}"
							],
							"path": [
								"api",
								"size"
							]
						}
					},
					"response": []
				},
				{
					"name": "create size",
					"request": {
						"method": "POST",
						"header": [
							{
								"key": "organizationId",
								"value": "{{organization_id}}",
								"type": "text"
							},
							{
								"key": "Accept",
								"value": "application/json",
								"type": "text"
							}
						],
						"body": {
							"mode": "formdata",
							"formdata": [
								{
									"key": "name",
									"value": "large",
									"type": "text"
								}
							]
						},
						"url": {
							"raw": "{{url}}/api/size",
							"host": [
								"{{url}}"
							],
							"path": [
								"api",
								"size"
							]
						}
					},
					"response": []
				},
				{
					"name": "update size",
					"request": {
						"method": "POST",
						"header": [
							{
								"key": "organizationId",
								"value": "{{organization_id}}",
								"type": "text"
							}
						],
						"body": {
							"mode": "formdata",
							"formdata": [
								{
									"key": "name",
									"value": "XXL",
									"type": "text"
								},
								{
									"key": "_method",
									"value": "PUT",
									"type": "text"
								}
							]
						},
						"url": {
							"raw": "{{url}}/api/size/:size_id",
							"host": [
								"{{url}}"
							],
							"path": [
								"api",
								"size",
								":size_id"
							],
							"variable": [
								{
									"key": "size_id",
									"value": "2"
								}
							]
						}
					},
					"response": []
				},
				{
					"name": "delete size",
					"request": {
						"method": "DELETE",
						"header": [
							{
								"key": "organizationId",
								"value": "{{organization_id}}",
								"type": "text"
							}
						],
						"body": {
							"mode": "formdata",
							"formdata": []
						},
						"url": {
							"raw": "{{url}}/api/size/:size_id",
							"host": [
								"{{url}}"
							],
							"path": [
								"api",
								"size",
								":size_id"
							],
							"variable": [
								{
									"key": "size_id",
									"value": "2"
								}
							]
						}
					},
					"response": []
				},
				{
					"name": "get single size",
					"protocolProfileBehavior": {
						"disableBodyPruning": true
					},
					"request": {
						"method": "GET",
						"header": [
							{
								"key": "organizationId",
								"value": "{{organization_id}}",
								"type": "text"
							}
						],
						"body": {
							"mode": "formdata",
							"formdata": []
						},
						"url": {
							"raw": "{{url}}/api/size/:size_id",
							"host": [
								"{{url}}"
							],
							"path": [
								"api",
								"size",
								":size_id"
							],
							"variable": [
								{
									"key": "size_id",
									"value": "3"
								}
							]
						}
					},
					"response": []
				}
			]
		},
		{
			"name": "actual data",
			"item": [
				{
					"name": "actual order data",
					"request": {
						"method": "GET",
						"header": [
							{
								"key": "organizationId",
								"value": "{{organization_id}}",
								"type": "text"
							}
						],
						"url": {
							"raw": "{{url}}/api/inventory-forecast/:client_id/actual",
							"host": [
								"{{url}}"
							],
							"path": [
								"api",
								"inventory-forecast",
								":client_id",
								"actual"
							],
							"variable": [
								{
									"key": "client_id",
									"value": "1"
								}
							]
						}
					},
					"response": []
				},
				{
					"name": "actual order data for multiple clients",
					"request": {
						"method": "POST",
						"header": [
							{
								"key": "organizationId",
								"value": "{{organization_id}}",
								"type": "text"
							}
						],
						"body": {
							"mode": "raw",
							"raw": "{\r\n    \"client_ids\": [\r\n        \"1a\",\r\n        \"1\"\r\n    ]\r\n}",
							"options": {
								"raw": {
									"language": "json"
								}
							}
						},
						"url": {
							"raw": "{{url}}/api/inventory-forecast/:date/actual",
							"host": [
								"{{url}}"
							],
							"path": [
								"api",
								"inventory-forecast",
								":date",
								"actual"
							],
							"variable": [
								{
									"key": "date",
									"value": "2022-12-01"
								}
							]
						}
					},
					"response": []
				}
			]
		}
	],
	"auth": {
		"type": "bearer",
		"bearer": [
			{
				"key": "token",
				"value": "{{access_token}}",
				"type": "string"
			}
		]
	},
	"event": [
		{
			"listen": "prerequest",
			"script": {
				"type": "text/javascript",
				"exec": [
					""
				]
			}
		},
		{
			"listen": "test",
			"script": {
				"type": "text/javascript",
				"exec": [
					""
				]
			}
		}
	]
}